django_emailsupport
