Metadata-Version: 1.1
Name: django-emailsupport
Version: 0.0.3
Summary: Simple email support over django admin
Home-page: https://github.com/rosti-cz/django-emailsupport
Author: Martin Voldrich
Author-email: rbas.cz@gmail.com
License: MIT
Platform: UNKNOWN
Classifier: Development Status :: 3 - Alpha
Classifier: Intended Audience :: Developers
Classifier: License :: OSI Approved :: MIT License
Classifier: Programming Language :: Python
Classifier: Programming Language :: Python :: 2.6
Classifier: Programming Language :: Python :: 2.7
Classifier: Topic :: Software Development :: Libraries :: Python Modules
Classifier: Topic :: Internet
